[{"_index":"handbook","_type":"_doc","id":"OBEBJnMByMrymAEmCDvl","_score":1,"_source":{"Episode":"The Pro Version: Listener Questions (with Ayo Edebiri)","speaker":"spk_0","startTime":675.68,"text":"A lot of people geniu's online","PodcastName":"The Ads Version: Hollywood Handbook","tags":[]}},{"_index":"handbook","_type":"_doc","id":"QBEBJnMByMrymAEmCDvl","_score":1,"_source":{"Episode":"The Pro Version: Listener Questions (with Ayo Edebiri)","speaker":"spk_1","startTime":716.8,"text":"You 'say I had to give me a pep tal.","PodcastName":"The Ads Version: Hollywood Handbook","tags":[]}},{"_index":"handbook","_type":"_doc","id":"SREBJnMByMrymAEmCDvl","_score":1,"_source":{"Episode":"The Pro Version: Listener Questions (with Ayo Edebiri)","speaker":"spk_1","startTime":773.9,"text":"There''s a fir'st of all, there''s Mom.","PodcastName":"The Ads Version: Hollywood Handbook","tags":[]}},{"_index":"handbook","_type":"_doc","id":"TxEBJnMByMrymAEmCDvl","_score":1,"_source":{"Episode":"The Pro Version: Listener Questions (with Ayo Edebiri)","speaker":"spk_0","startTime":800.33,"text":"Hi, honey. And-Away Cub's little brother. Hand me that.","PodcastName":"The Ads Version: Hollywood Handbook","tags":["Cub"]}},{"_index":"handbook","_type":"_doc","id":"XhEBJnMByMrymAEmCDvl","_score":1,"_source":{"Episode":"The Pro Version: Listener Questions (with Ayo Edebiri)","speaker":"spk_3","startTime":923.1,"text":"DP. I need Judd to 'see my 'stuff.","PodcastName":"The Ads Version: Hollywood Handbook","tags":["Judd"]}},{"_index":"handbook","_type":"_doc","id":"XxEBJnMByMrymAEmCDvl","_score":1,"_source":{"Episode":"The Pro Version: Listener Questions (with Ayo Edebiri)","speaker":"spk_1","startTime":926.73,"text":"What''s weird i's we're entering an era where you could ba'sically dio Ray again with Jamie Foxx. But he ju'st, like, take's the 'sungla's'se's off and i's Jamie Foxx.","PodcastName":"The Ads Version: Hollywood Handbook","tags":["Ray","Jamie Foxx","sungla's'se","Jamie Foxx"]}},{"_index":"handbook","_type":"_doc","id":"aREBJnMByMrymAEmCDvl","_score":1,"_source":{"Episode":"The Pro Version: Listener Questions (with Ayo Edebiri)","speaker":"spk_0","startTime":1001.09,"text":"Right? Okay, I So OK, an'swering the 'second que'stion, I would like to 'see Mr Being get a movie.","PodcastName":"The Ads Version: Hollywood Handbook","tags":["Mr Being"]}},{"_index":"handbook","_type":"_doc","id":"bhEBJnMByMrymAEmCDvl","_score":1,"_source":{"Episode":"The Pro Version: Listener Questions (with Ayo Edebiri)","speaker":"spk_3","startTime":1027.64,"text":"ah, at long la'st, I ju'st 'saw 'something Riel finally","PodcastName":"The Ads Version: Hollywood Handbook","tags":["Riel"]}},{"_index":"handbook","_type":"_doc","id":"cxEBJnMByMrymAEmCDvl","_score":1,"_source":{"Episode":"The Pro Version: Listener Questions (with Ayo Edebiri)","speaker":"spk_1","startTime":1057.22,"text":"during doe's engineer Jordan","PodcastName":"The Ads Version: Hollywood Handbook","tags":["Jordan"]}},{"_index":"handbook","_type":"_doc","id":"gREBJnMByMrymAEmCDvl","_score":1,"_source":{"Episode":"The Pro Version: Listener Questions (with Ayo Edebiri)","speaker":"spk_3","startTime":1120.65,"text":"ju'st 'sick to my 'stomach before he","PodcastName":"The Ads Version: Hollywood Handbook","tags":[]}},{"_index":"handbook","_type":"_doc","id":"jBEBJnMByMrymAEmCDvl","_score":1,"_source":{"Episode":"The Pro Version: Listener Questions (with Ayo Edebiri)","speaker":"spk_3","startTime":1203.62,"text":"And if you're bad, then God pick's the body for you If your behavior in heaven","PodcastName":"The Ads Version: Hollywood Handbook","tags":["God"]}},{"_index":"handbook","_type":"_doc","id":"kBEBJnMByMrymAEmCDvl","_score":1,"_source":{"Episode":"The Pro Version: Listener Questions (with Ayo Edebiri)","speaker":"spk_3","startTime":1220.95,"text":"He wa's bad 's","PodcastName":"The Ads Version: Hollywood Handbook","tags":[]}},{"_index":"handbook","_type":"_doc","id":"kxEBJnMByMrymAEmCDvl","_score":1,"_source":{"Episode":"The Pro Version: Listener Questions (with Ayo Edebiri)","speaker":"spk_0","startTime":1241.57,"text":"Are you making that? I want to 'see that dough. I want u's and I want to 'see dem benefit's.","PodcastName":"The Ads Version: Hollywood Handbook","tags":[]}},{"_index":"handbook","_type":"_doc","id":"lxEBJnMByMrymAEmCDvl","_score":1,"_source":{"Episode":"The Pro Version: Listener Questions (with Ayo Edebiri)","speaker":"spk_1","startTime":1289.85,"text":"I have a que'stion for Bo'sch Bo'sch. Doe's Tony know your name?","PodcastName":"The Ads Version: Hollywood Handbook","tags":["Bo'sch","Bo'sch","Doe","Tony"]}},{"_index":"handbook","_type":"_doc","id":"mxEBJnMByMrymAEmCDvl","_score":1,"_source":{"Episode":"The Pro Version: Listener Questions (with Ayo Edebiri)","speaker":"spk_1","startTime":1332.34,"text":"Um, I like that. Something that al'so you are. Bo'sh i's bolu's.","PodcastName":"The Ads Version: Hollywood Handbook","tags":["bolu"]}},{"_index":"handbook","_type":"_doc","id":"pREBJnMByMrymAEmCDvl","_score":1,"_source":{"Episode":"The Pro Version: Listener Questions (with Ayo Edebiri)","speaker":"spk_3","startTime":1372.34,"text":"Tony doe's Nobody day, but he think's My Davi's early.","PodcastName":"The Ads Version: Hollywood Handbook","tags":["Tony","My Davi"]}},{"_index":"handbook","_type":"_doc","id":"tBEBJnMByMrymAEmCDvl","_score":1,"_source":{"Episode":"The Pro Version: Listener Questions (with Ayo Edebiri)","speaker":"spk_0","startTime":1463.95,"text":"that''s not what","PodcastName":"The Ads Version: Hollywood Handbook","tags":[]}},{"_index":"handbook","_type":"_doc","id":"uhEBJnMByMrymAEmCDvl","_score":1,"_source":{"Episode":"The Pro Version: Listener Questions (with Ayo Edebiri)","speaker":"spk_0","startTime":1490.16,"text":"It''s not the dog part here. You go","PodcastName":"The Ads Version: Hollywood Handbook","tags":[]}},{"_index":"handbook","_type":"_doc","id":"vBEBJnMByMrymAEmCDvl","_score":1,"_source":{"Episode":"The Pro Version: Listener Questions (with Ayo Edebiri)","speaker":"spk_0","startTime":1503.34,"text":"So every time","PodcastName":"The Ads Version: Hollywood Handbook","tags":[]}},{"_index":"handbook","_type":"_doc","id":"vhEBJnMByMrymAEmCDvl","_score":1,"_source":{"Episode":"The Pro Version: Listener Questions (with Ayo Edebiri)","speaker":"spk_1","startTime":1509.49,"text":"Bo'sch leg's to turn everyone ago of chicken nugget's, that''s 'sick. So that z","PodcastName":"The Ads Version: Hollywood Handbook","tags":[]}},{"_index":"handbook","_type":"_doc","id":"whEBJnMByMrymAEmCDvl","_score":1,"_source":{"Episode":"The Pro Version: Listener Questions (with Ayo Edebiri)","speaker":"spk_2","startTime":1526.26,"text":"Doe's it?","PodcastName":"The Ads Version: Hollywood Handbook","tags":[]}},{"_index":"handbook","_type":"_doc","id":"xBEBJnMByMrymAEmCDvl","_score":1,"_source":{"Episode":"The Pro Version: Listener Questions (with Ayo Edebiri)","speaker":"spk_1","startTime":1532.64,"text":"right if you ju'st get cla's'sic joke's Triplet's, trick's on why I wi'sh Word's if you ju'st look a cla's'sic joke 'structure","PodcastName":"The Ads Version: Hollywood Handbook","tags":["cla's'sic","Triplet","cla's'sic"]}},{"_index":"handbook","_type":"_doc","id":"xREBJnMByMrymAEmCDvl","_score":1,"_source":{"Episode":"The Pro Version: Listener Questions (with Ayo Edebiri)","speaker":"spk_2","startTime":1543.18,"text":"mu'sical. Jeffrey Dahmer wa's in Milwaukee.","PodcastName":"The Ads Version: Hollywood Handbook","tags":["Jeffrey Dahmer","Milwaukee"]}},{"_index":"handbook","_type":"_doc","id":"yBEBJnMByMrymAEmCDvl","_score":1,"_source":{"Episode":"The Pro Version: Listener Questions (with Ayo Edebiri)","speaker":"spk_3","startTime":1572.99,"text":"So we have you. You","PodcastName":"The Ads Version: Hollywood Handbook","tags":[]}},{"_index":"handbook","_type":"_doc","id":"zBEBJnMByMrymAEmCDvl","_score":1,"_source":{"Episode":"The Pro Version: Listener Questions (with Ayo Edebiri)","speaker":"spk_0","startTime":1609.55,"text":"e'so who famou'sly died in 1988","PodcastName":"The Ads Version: Hollywood Handbook","tags":[]}},{"_index":"handbook","_type":"_doc","id":"zhEBJnMByMrymAEmCDvl","_score":1,"_source":{"Episode":"The Pro Version: Listener Questions (with Ayo Edebiri)","speaker":"spk_3","startTime":1619.68,"text":"I really don't think 'so.","PodcastName":"The Ads Version: Hollywood Handbook","tags":[]}},{"_index":"handbook","_type":"_doc","id":"zxEBJnMByMrymAEmCDvl","_score":1,"_source":{"Episode":"The Pro Version: Listener Questions (with Ayo Edebiri)","speaker":"spk_0","startTime":1622.47,"text":"I'm, like, feeling But I could be wrong, but I feel like I'm right.","PodcastName":"The Ads Version: Hollywood Handbook","tags":[]}},{"_index":"handbook","_type":"_doc","id":"1hEBJnMByMrymAEmCDvl","_score":1,"_source":{"Episode":"The Pro Version: Listener Questions (with Ayo Edebiri)","speaker":"spk_0","startTime":1667.09,"text":"It''s pretty much exactly Oh, yeah, it''s pretty much right. And it''s al'so like braid. It''s like, brave a feat. What?","PodcastName":"The Ads Version: Hollywood Handbook","tags":["braid"]}},{"_index":"handbook","_type":"_doc","id":"4BEBJnMByMrymAEmCDvl","_score":1,"_source":{"Episode":"The Pro Version: Listener Questions (with Ayo Edebiri)","speaker":"spk_3","startTime":1712.99,"text":"how we dealt with it?","PodcastName":"The Ads Version: Hollywood Handbook","tags":[]}},{"_index":"handbook","_type":"_doc","id":"4hEBJnMByMrymAEmCDvl","_score":1,"_source":{"Episode":"The Pro Version: Listener Questions (with Ayo Edebiri)","speaker":"spk_3","startTime":1751.06,"text":"Healy''s 'skitch","PodcastName":"The Ads Version: Hollywood Handbook","tags":["Healy"]}},{"_index":"handbook","_type":"_doc","id":"5BEBJnMByMrymAEmCDvl","_score":1,"_source":{"Episode":"The Pro Version: Listener Questions (with Ayo Edebiri)","speaker":"spk_1","startTime":1769.76,"text":"women decorum","PodcastName":"The Ads Version: Hollywood Handbook","tags":[]}},{"_index":"handbook","_type":"_doc","id":"9BEBJnMByMrymAEmCDvl","_score":1,"_source":{"Episode":"The Pro Version: Listener Questions (with Ayo Edebiri)","speaker":"spk_0","startTime":1859.44,"text":"have to read it becau'se one of them. I a's'sume the guy. Ye's. The guy write's al'so, um, you like Joanna New'som and Hollywood Handbook too. Damn, my two favorite thing's have often wondered if anyone el'se on Earth 'shared the'se inter'secting intere'st's. Law. Oh, wait. No, She wrote that. And then he 'said, Yeah, literally My to faith thing's to Will you marry me? She 'said, And 'she 'said, TBH yacht. Now what''s that? Walker. Loui'siana i's where he i's. Where wa's 'she?","PodcastName":"The Ads Version: Hollywood Handbook","tags":["Joanna New'som","Hollywood Handbook","Earth","Law","Will","Loui'siana"]}},{"_index":"handbook","_type":"_doc","id":"ExEBJnMByMrymAEmCDzl","_score":1,"_source":{"Episode":"The Pro Version: Listener Questions (with Ayo Edebiri)","speaker":"spk_3","startTime":2086.41,"text":"You got to get in there with a Runge.","PodcastName":"The Ads Version: Hollywood Handbook","tags":[]}},{"_index":"handbook","_type":"_doc","id":"FxEBJnMByMrymAEmCDzl","_score":1,"_source":{"Episode":"The Pro Version: Listener Questions (with Ayo Edebiri)","speaker":"spk_1","startTime":2106.7,"text":"Thank you. Good. Lola,","PodcastName":"The Ads Version: Hollywood Handbook","tags":["Lola"]}},{"_index":"handbook","_type":"_doc","id":"GREBJnMByMrymAEmCDzl","_score":1,"_source":{"Episode":"The Pro Version: Listener Questions (with Ayo Edebiri)","speaker":"spk_1","startTime":2110.78,"text":"Ju'st loo'sen up all the gear's, do yoga.","PodcastName":"The Ads Version: Hollywood Handbook","tags":[]}},{"_index":"handbook","_type":"_doc","id":"GhEBJnMByMrymAEmCDzl","_score":1,"_source":{"Episode":"The Pro Version: Listener Questions (with Ayo Edebiri)","speaker":"spk_3","startTime":2114.5,"text":"The waterbed part. Really un'settling becau'se it''s not Ripple, you're out. It''s very du'sty,","PodcastName":"The Ads Version: Hollywood Handbook","tags":[]}},{"_index":"handbook","_type":"_doc","id":"GxEBJnMByMrymAEmCDzl","_score":1,"_source":{"Episode":"The Pro Version: Listener Questions (with Ayo Edebiri)","speaker":"spk_2","startTime":2126.32,"text":"gentlemen. If all the Earwolf employee's ho'st's included had a fight to the death, who would be the la'st per'son 'standing from Jake? Okay, then we do thi's. Probably a guy from Turbo Start.","PodcastName":"The Ads Version: Hollywood Handbook","tags":["Earwolf","Jake","Turbo Start"]}},{"_index":"handbook","_type":"_doc","id":"HBEBJnMByMrymAEmCDzl","_score":1,"_source":{"Episode":"The Pro Version: Listener Questions (with Ayo Edebiri)","speaker":"spk_0","startTime":2140.5,"text":"I think it''s Jake from Turbo 'started. Sad that I'd like know who all the'se people are. Almo'st. Yeah. Except for the couple. That''s like in love. Yeah, becau'se of you guy's. Becau'se","PodcastName":"The Ads Version: Hollywood Handbook","tags":["Jake","Turbo"]}},{"_index":"handbook","_type":"_doc","id":"HxEBJnMByMrymAEmCDzl","_score":1,"_source":{"Episode":"The Pro Version: Listener Questions (with Ayo Edebiri)","speaker":"spk_1","startTime":2163.47,"text":"I wa's humiliated. Hone'stly,","PodcastName":"The Ads Version: Hollywood Handbook","tags":[]}},{"_index":"handbook","_type":"_doc","id":"IxEBJnMByMrymAEmCDzl","_score":1,"_source":{"Episode":"The Pro Version: Listener Questions (with Ayo Edebiri)","speaker":"spk_2","startTime":2179.34,"text":"que'stion's. I'm thinking about getting it's head to What 'should I get? And that wa's un'signed. Um,","PodcastName":"The Ads Version: Hollywood Handbook","tags":[]}},{"_index":"handbook","_type":"_doc","id":"JhEBJnMByMrymAEmCDzl","_score":1,"_source":{"Episode":"The Pro Version: Listener Questions (with Ayo Edebiri)","speaker":"spk_1","startTime":2235.74,"text":"i's a waning cre'scent? And what i's profe's'sorial,","PodcastName":"The Ads Version: Hollywood Handbook","tags":[]}},{"_index":"handbook","_type":"_doc","id":"KBEBJnMByMrymAEmCDzl","_score":1,"_source":{"Episode":"The Pro Version: Listener Questions (with Ayo Edebiri)","speaker":"spk_1","startTime":2248.29,"text":"And then he i's that What about that guy Could look","PodcastName":"The Ads Version: Hollywood Handbook","tags":[]}},{"_index":"handbook","_type":"_doc","id":"KhEBJnMByMrymAEmCDzl","_score":1,"_source":{"Episode":"The Pro Version: Listener Questions (with Ayo Edebiri)","speaker":"spk_1","startTime":2262.9,"text":"Um, having a good one. Evan idea.","PodcastName":"The Ads Version: Hollywood Handbook","tags":["Evan"]}},{"_index":"handbook","_type":"_doc","id":"LhEBJnMByMrymAEmCDzl","_score":1,"_source":{"Episode":"The Pro Version: Listener Questions (with Ayo Edebiri)","speaker":"spk_1","startTime":2300.75,"text":"Let her go by pa's'senger's.","PodcastName":"The Ads Version: Hollywood Handbook","tags":[]}},{"_index":"handbook","_type":"_doc","id":"MhEBJnMByMrymAEmCDzl","_score":1,"_source":{"Episode":"The Pro Version: Listener Questions (with Ayo Edebiri)","speaker":"spk_1","startTime":2340.76,"text":"a 'song we wrote. Kind of about","PodcastName":"The Ads Version: Hollywood Handbook","tags":[]}},{"_index":"handbook","_type":"_doc","id":"NREBJnMByMrymAEmCDzl","_score":1,"_source":{"Episode":"The Pro Version: Listener Questions (with Ayo Edebiri)","speaker":"spk_0","startTime":2359.82,"text":"I think that that 'song wa's about doing Molly in the club. Ha about","PodcastName":"The Ads Version: Hollywood Handbook","tags":["Molly"]}},{"_index":"handbook","_type":"_doc","id":"NhEBJnMByMrymAEmCDzl","_score":1,"_source":{"Episode":"The Pro Version: Listener Questions (with Ayo Edebiri)","speaker":"spk_3","startTime":2364.83,"text":"I thought it wa's about chicken baguette.","PodcastName":"The Ads Version: Hollywood Handbook","tags":[]}},{"_index":"handbook","_type":"_doc","id":"OREBJnMByMrymAEmCDzl","_score":1,"_source":{"Episode":"The Pro Version: Listener Questions (with Ayo Edebiri)","speaker":"spk_0","startTime":2393.47,"text":"Okay, Sam. Okay. And there might be kind of like an intere'sting que'stion to a'sk right now. Uh, monkey up a little higher. Did you lo'se it? I's what the que'stion.","PodcastName":"The Ads Version: Hollywood Handbook","tags":["Sam"]}},{"_index":"handbook","_type":"_doc","id":"PxEBJnMByMrymAEmCDzl","_score":1,"_source":{"Episode":"The Pro Version: Listener Questions (with Ayo Edebiri)","speaker":"spk_0","startTime":2427.26,"text":"Oh, God''s ab. What are you a'sking me right now?","PodcastName":"The Ads Version: Hollywood Handbook","tags":[]}},{"_index":"handbook","_type":"_doc","id":"RhEBJnMByMrymAEmCDzl","_score":1,"_source":{"Episode":"The Pro Version: Listener Questions (with Ayo Edebiri)","speaker":"spk_0","startTime":2458.34,"text":"I 'said Haye's, what''s going on, Shawn? Okay, I'm gonna try it. Okay? I 'said what''s going charm? Tho'se are both good. They're both good. Like","PodcastName":"The Ads Version: Hollywood Handbook","tags":["Haye","Shawn"]}},{"_index":"handbook","_type":"_doc","id":"ShEBJnMByMrymAEmCDzl","_score":1,"_source":{"Episode":"The Pro Version: Listener Questions (with Ayo Edebiri)","speaker":"spk_3","startTime":2493.12,"text":"what''s going","PodcastName":"The Ads Version: Hollywood Handbook","tags":[]}},{"_index":"handbook","_type":"_doc","id":"SxEBJnMByMrymAEmCDzl","_score":1,"_source":{"Episode":"The Pro Version: Listener Questions (with Ayo Edebiri)","speaker":"spk_0","startTime":2495.21,"text":"on. Have you found the que'stion yet? Sam? It wa's like, Have you ever been feeling like you cru'shed Search cru'shed control have fre'sh upright. It wa's it Wa's it up wa's up the 'shirt's up. Oh, oh, it wa'sn't. Gentlemen,","PodcastName":"The Ads Version: Hollywood Handbook","tags":["Sam"]}},{"_index":"handbook","_type":"_doc","id":"UBEBJnMByMrymAEmCDzl","_score":1,"_source":{"Episode":"The Pro Version: Listener Questions (with Ayo Edebiri)","speaker":"spk_0","startTime":2548.31,"text":"My gut's ju'st 'started. Feel like I actually di'sk ru'shed it right now","PodcastName":"The Ads Version: Hollywood Handbook","tags":[]}},{"_index":"handbook","_type":"_doc","id":"UhEBJnMByMrymAEmCDzl","_score":1,"_source":{"Episode":"The Pro Version: Listener Questions (with Ayo Edebiri)","speaker":"spk_1","startTime":0,"text":"The-Pro Ver'sion.","PodcastName":"The Ads Version: Hollywood Handbook","tags":["The-","Pro"]}},{"_index":"handbook","_type":"_doc","id":"VxEBJnMByMrymAEmZjyg","_score":1,"_source":{"Episode":"Jeremy Levick and Rajat Suresh, Our Close Friends","speaker":"spk_1","startTime":29.13,"text":"remind me, And now you 'set u's up, huh? So remind me what her like, what her deal i's. She went to high 'school with me. Um, we were in the","PodcastName":"The Ads Version: Hollywood Handbook","tags":[]}},{"_index":"handbook","_type":"_doc","id":"YREBJnMByMrymAEmZjyg","_score":1,"_source":{"Episode":"Jeremy Levick and Rajat Suresh, Our Close Friends","speaker":"spk_2","startTime":234.34,"text":"No, I Did okay. No, I did. Ah,","PodcastName":"The Ads Version: Hollywood Handbook","tags":[]}},{"_index":"handbook","_type":"_doc","id":"YxEBJnMByMrymAEmZjyg","_score":1,"_source":{"Episode":"Jeremy Levick and Rajat Suresh, Our Close Friends","speaker":"spk_2","startTime":245.35,"text":"not May, Um,","PodcastName":"The Ads Version: Hollywood Handbook","tags":["May"]}},{"_index":"handbook","_type":"_doc","id":"ehEBJnMByMrymAEmZjyg","_score":1,"_source":{"Episode":"Jeremy Levick and Rajat Suresh, Our Close Friends","speaker":"spk_0","startTime":522.97,"text":"be happy for one another. Yeah.","PodcastName":"The Ads Version: Hollywood Handbook","tags":[]}},{"_index":"handbook","_type":"_doc","id":"hREBJnMByMrymAEmZjyg","_score":1,"_source":{"Episode":"Jeremy Levick and Rajat Suresh, Our Close Friends","speaker":"spk_0","startTime":586.06,"text":"I wa's on who? I watched Dev''s. Okay, you guy's watch thi's Ju'st 'so intere'sting to come on thi's 'show on Earwolf 'showing","PodcastName":"The Ads Version: Hollywood Handbook","tags":["Dev","Ju'st","Earwolf"]}},{"_index":"handbook","_type":"_doc","id":"iBEBJnMByMrymAEmZjyg","_score":1,"_source":{"Episode":"Jeremy Levick and Rajat Suresh, Our Close Friends","speaker":"spk_2","startTime":614.78,"text":"Yeah, I know. It''s a 'signal. Mean we love becau'se I've watched it before. Yeah, and we love okay. You didn't like it.","PodcastName":"The Ads Version: Hollywood Handbook","tags":[]}},{"_index":"handbook","_type":"_doc","id":"jxEBJnMByMrymAEmZjyg","_score":1,"_source":{"Episode":"Jeremy Levick and Rajat Suresh, Our Close Friends","speaker":"spk_1","startTime":695.37,"text":"flinch, Lynch. The an'swer i's flinched. North Carolina to fall inching. Brat! What did you watch la'st night?","PodcastName":"The Ads Version: Hollywood Handbook","tags":["Lynch","North Carolina"]}},{"_index":"handbook","_type":"_doc","id":"mxEBJnMByMrymAEmZjyg","_score":1,"_source":{"Episode":"Jeremy Levick and Rajat Suresh, Our Close Friends","speaker":"spk_1","startTime":802.25,"text":"I know may. I'm not like driving at anyone 'specific. I ju'st like who? Uh,","PodcastName":"The Ads Version: Hollywood Handbook","tags":["may"]}},{"_index":"handbook","_type":"_doc","id":"nREBJnMByMrymAEmZjyg","_score":1,"_source":{"Episode":"Jeremy Levick and Rajat Suresh, Our Close Friends","speaker":"spk_1","startTime":823.58,"text":"all I did wa's freakin go to your college, Jeremy, and actually teach you about what comedy i'sn't. How to dio, maybe? Yeah. Sorry. I didn't over'stay like, hit a button for you from my hou'se, actually went all the way to your college And did ah, lecture Siri's for you?","PodcastName":"The Ads Version: Hollywood Handbook","tags":["Jeremy","Siri"]}},{"_index":"handbook","_type":"_doc","id":"pREBJnMByMrymAEmZjyg","_score":1,"_source":{"Episode":"Jeremy Levick and Rajat Suresh, Our Close Friends","speaker":"spk_1","startTime":882.84,"text":"Let''s talk about the video becau'se people aren't going to know what the fuck we're talking about when we 'say that you guy's air here.","PodcastName":"The Ads Version: Hollywood Handbook","tags":[]}},{"_index":"handbook","_type":"_doc","id":"phEBJnMByMrymAEmZjyg","_score":1,"_source":{"Episode":"Jeremy Levick and Rajat Suresh, Our Close Friends","speaker":"spk_2","startTime":889.31,"text":"Yeah, They're not going to know what the fuck we mean. But when we talk about the video now you've got their attention. That''s right.","PodcastName":"The Ads Version: Hollywood Handbook","tags":[]}},{"_index":"handbook","_type":"_doc","id":"pxEBJnMByMrymAEmZjyg","_score":1,"_source":{"Episode":"Jeremy Levick and Rajat Suresh, Our Close Friends","speaker":"spk_0","startTime":901.08,"text":"Oh, eye's it right here. Okay. Brett ha's 'shared hi's 'screen,","PodcastName":"The Ads Version: Hollywood Handbook","tags":["Brett"]}},{"_index":"handbook","_type":"_doc","id":"rBEBJnMByMrymAEmZjyg","_score":1,"_source":{"Episode":"Jeremy Levick and Rajat Suresh, Our Close Friends","speaker":"spk_0","startTime":934.91,"text":"Do we? So I mean, like, I don't know if I need to watch thi's whole thing. That maybe it could ju'st be de'scribed to May. But we have a year.","PodcastName":"The Ads Version: Hollywood Handbook","tags":["May"]}},{"_index":"handbook","_type":"_doc","id":"sBEBJnMByMrymAEmZjyg","_score":1,"_source":{"Episode":"Jeremy Levick and Rajat Suresh, Our Close Friends","speaker":"spk_0","startTime":955.74,"text":"i's what i's it?","PodcastName":"The Ads Version: Hollywood Handbook","tags":[]}},{"_index":"handbook","_type":"_doc","id":"sREBJnMByMrymAEmZjyg","_score":1,"_source":{"Episode":"Jeremy Levick and Rajat Suresh, Our Close Friends","speaker":"spk_1","startTime":957.13,"text":"What happened? Well,","PodcastName":"The Ads Version: Hollywood Handbook","tags":[]}},{"_index":"handbook","_type":"_doc","id":"sxEBJnMByMrymAEmZjyg","_score":1,"_source":{"Episode":"Jeremy Levick and Rajat Suresh, Our Close Friends","speaker":"spk_1","startTime":988.78,"text":"But we did 'something. Exactly. Yeah, we did. Something el'se are not ba'sed on Gilly. Um Gilli's. Shane Gila Single. Yeah. Really? There''s, ah, video that went viral of 'shame Gilli's on hi's podca'st. Kind of riffing and being raci'st. And we did our own little 'spin on that, right? Huh?","PodcastName":"The Ads Version: Hollywood Handbook","tags":["Gilly","Gilli","Shane Gila","Gilli"]}},{"_index":"handbook","_type":"_doc","id":"tBEBJnMByMrymAEmZjyg","_score":1,"_source":{"Episode":"Jeremy Levick and Rajat Suresh, Our Close Friends","speaker":"spk_0","startTime":1010.62,"text":"What do you 'say","PodcastName":"The Ads Version: Hollywood Handbook","tags":[]}},{"_index":"handbook","_type":"_doc","id":"thEBJnMByMrymAEmZjyg","_score":1,"_source":{"Episode":"Jeremy Levick and Rajat Suresh, Our Close Friends","speaker":"spk_0","startTime":1016.33,"text":"What we 'say? Like we, like, talked about, Like, 'stuff like door's and thing's. Yeah. Why? What did you do that?","PodcastName":"The Ads Version: Hollywood Handbook","tags":[]}},{"_index":"handbook","_type":"_doc","id":"wBEBJnMByMrymAEmZjyg","_score":1,"_source":{"Episode":"Jeremy Levick and Rajat Suresh, Our Close Friends","speaker":"spk_1","startTime":1082.94,"text":"Yeah, I feel that owning like's, but that''s our video, but right? Choo'se toe. Watch it. You know what I mean?","PodcastName":"The Ads Version: Hollywood Handbook","tags":[]}},{"_index":"handbook","_type":"_doc","id":"xBEBJnMByMrymAEmZjyg","_score":1,"_source":{"Episode":"Jeremy Levick and Rajat Suresh, Our Close Friends","speaker":"spk_0","startTime":1103.45,"text":"um I gue's's toe like, make fun of 'shingle, i's's and Reich kind of 'shine a light on. But would you agree that I ju'st did that? Probably much more effectively","PodcastName":"The Ads Version: Hollywood Handbook","tags":[]}},{"_index":"handbook","_type":"_doc","id":"yxEBJnMByMrymAEmZjyg","_score":1,"_source":{"Episode":"Jeremy Levick and Rajat Suresh, Our Close Friends","speaker":"spk_2","startTime":1183.05,"text":"appetite? Uh, appetite for de'struction. Judd Apple. Ye's, I'd look at that.","PodcastName":"The Ads Version: Hollywood Handbook","tags":["Judd Apple"]}},{"_index":"handbook","_type":"_doc","id":"zhEBJnMByMrymAEmZjyg","_score":1,"_source":{"Episode":"Jeremy Levick and Rajat Suresh, Our Close Friends","speaker":"spk_2","startTime":1207.77,"text":"Do you 'see that? You 'see that the cartoon Viking avatar 'show up in your","PodcastName":"The Ads Version: Hollywood Handbook","tags":["Viking"]}},{"_index":"handbook","_type":"_doc","id":"0REBJnMByMrymAEmZjyg","_score":1,"_source":{"Episode":"Jeremy Levick and Rajat Suresh, Our Close Friends","speaker":"spk_1","startTime":1223.57,"text":"your girl? That a tad? Do you 'see that kind of gray pencil 'sketch cartoon? Viking?","PodcastName":"The Ads Version: Hollywood Handbook","tags":["Viking"]}},{"_index":"handbook","_type":"_doc","id":"4REBJnMByMrymAEmZjyg","_score":1,"_source":{"Episode":"Jeremy Levick and Rajat Suresh, Our Close Friends","speaker":"spk_0","startTime":1348.29,"text":"of conn 'satire. Exactly. We, like, 'send up people. Front line 'satiri'st's. Yeah. Why?","PodcastName":"The Ads Version: Hollywood Handbook","tags":[]}},{"_index":"handbook","_type":"_doc","id":"6hEBJnMByMrymAEmZjyg","_score":1,"_source":{"Episode":"Jeremy Levick and Rajat Suresh, Our Close Friends","speaker":"spk_1","startTime":1433.42,"text":"Oh, well, a's the arti'st who created Epi'sode 104 Locked Down, which wa's al'so a bit of a parity in a 'satire and captured 'some of the motif's from film's like","PodcastName":"The Ads Version: Hollywood Handbook","tags":["Locked"]}},{"_index":"handbook","_type":"_doc","id":"6xEBJnMByMrymAEmZjyg","_score":1,"_source":{"Episode":"Jeremy Levick and Rajat Suresh, Our Close Friends","speaker":"spk_2","startTime":1447.15,"text":"Alien Movie.","PodcastName":"The Ads Version: Hollywood Handbook","tags":["Alien Movie"]}},{"_index":"handbook","_type":"_doc","id":"8REBJnMByMrymAEmZjyg","_score":1,"_source":{"Episode":"Jeremy Levick and Rajat Suresh, Our Close Friends","speaker":"spk_1","startTime":1517.99,"text":"'sen'sitivity and the dramatic half, but al'so the comedy that''s inherent in the 'subject. So when the void exi'st's for material like thi's, uh, gone village? Yeah, group. How do you feel it? And and am I correct in a's'serting Haye's","PodcastName":"The Ads Version: Hollywood Handbook","tags":["Haye"]}},{"_index":"handbook","_type":"_doc","id":"ABEBJnMByMrymAEmZj2g","_score":1,"_source":{"Episode":"Jeremy Levick and Rajat Suresh, Our Close Friends","speaker":"spk_1","startTime":1645.53,"text":"I's that what doe's that do? Big?","PodcastName":"The Ads Version: Hollywood Handbook","tags":[]}},{"_index":"handbook","_type":"_doc","id":"ChEBJnMByMrymAEmZj2g","_score":1,"_source":{"Episode":"Jeremy Levick and Rajat Suresh, Our Close Friends","speaker":"spk_2","startTime":1703.87,"text":"Yeah, that que'stion's confu'sing, though. It''s really hard. It","PodcastName":"The Ads Version: Hollywood Handbook","tags":["confu'sing"]}},{"_index":"handbook","_type":"_doc","id":"EhEBJnMByMrymAEmZj2g","_score":1,"_source":{"Episode":"Jeremy Levick and Rajat Suresh, Our Close Friends","speaker":"spk_2","startTime":1779.79,"text":"your they re throwing up.","PodcastName":"The Ads Version: Hollywood Handbook","tags":[]}},{"_index":"handbook","_type":"_doc","id":"FBEBJnMByMrymAEmZj2g","_score":1,"_source":{"Episode":"Jeremy Levick and Rajat Suresh, Our Close Friends","speaker":"spk_0","startTime":1792.62,"text":"Brett, why'd you do what''s what''s a man man 'song?","PodcastName":"The Ads Version: Hollywood Handbook","tags":["Brett","a man man"]}},{"_index":"handbook","_type":"_doc","id":"FREBJnMByMrymAEmZj2g","_score":1,"_source":{"Episode":"Jeremy Levick and Rajat Suresh, Our Close Friends","speaker":"spk_1","startTime":1796.75,"text":"What i's one? Ah, future peg. What did you do? Future pig Why Did Thi's Get Made?","PodcastName":"The Ads Version: Hollywood Handbook","tags":["Thi"]}},{"_index":"handbook","_type":"_doc","id":"GREBJnMByMrymAEmZj2g","_score":1,"_source":{"Episode":"Jeremy Levick and Rajat Suresh, Our Close Friends","speaker":"spk_0","startTime":1826.91,"text":"buying that 'sick. That really bring's me back to my la'st video when that happened for u's. Totally. What video i's that?","PodcastName":"The Ads Version: Hollywood Handbook","tags":[]}},{"_index":"handbook","_type":"_doc","id":"HhEBJnMByMrymAEmZj2g","_score":1,"_source":{"Episode":"Jeremy Levick and Rajat Suresh, Our Close Friends","speaker":"spk_0","startTime":1889.73,"text":"That''s a good thing that didn't happen Now, Ray,","PodcastName":"The Ads Version: Hollywood Handbook","tags":["Ray"]}},{"_index":"handbook","_type":"_doc","id":"IhEBJnMByMrymAEmZj2g","_score":1,"_source":{"Episode":"Jeremy Levick and Rajat Suresh, Our Close Friends","speaker":"spk_2","startTime":1921.43,"text":"the ho'spital's being overwhelmed, but right? Of cour'se. No,","PodcastName":"The Ads Version: Hollywood Handbook","tags":[]}},{"_index":"handbook","_type":"_doc","id":"IxEBJnMByMrymAEmZj2g","_score":1,"_source":{"Episode":"Jeremy Levick and Rajat Suresh, Our Close Friends","speaker":"spk_0","startTime":1925.27,"text":"I think it''s good to laugh. I ju'st don't know if that''s what we 'should laugh at Haye's to you. I wa'sn't 'sure. What do you think would be good to laugh at","PodcastName":"The Ads Version: Hollywood Handbook","tags":["Haye"]}},{"_index":"handbook","_type":"_doc","id":"JREBJnMByMrymAEmZj2g","_score":1,"_source":{"Episode":"Jeremy Levick and Rajat Suresh, Our Close Friends","speaker":"spk_1","startTime":1936.23,"text":"Ah, I gue's's um, maybe 'someone who i's, like, evil bad or 'someone who''s like intentionally trying to make people 'sick in'stead of people that are trying THOMAS make them not anymore and help them live. Totally. Yeah. No, I don't think","PodcastName":"The Ads Version: Hollywood Handbook","tags":[]}},{"_index":"handbook","_type":"_doc","id":"JhEBJnMByMrymAEmZj2g","_score":1,"_source":{"Episode":"Jeremy Levick and Rajat Suresh, Our Close Friends","speaker":"spk_0","startTime":1950.12,"text":"that''s really what I would probably","PodcastName":"The Ads Version: Hollywood Handbook","tags":[]}},{"_index":"handbook","_type":"_doc","id":"LREBJnMByMrymAEmZj2g","_score":1,"_source":{"Episode":"Jeremy Levick and Rajat Suresh, Our Close Friends","speaker":"spk_1","startTime":2005.9,"text":"Ray. Oh, you 'some of that.","PodcastName":"The Ads Version: Hollywood Handbook","tags":["Ray"]}},{"_index":"handbook","_type":"_doc","id":"LhEBJnMByMrymAEmZj2g","_score":1,"_source":{"Episode":"Jeremy Levick and Rajat Suresh, Our Close Friends","speaker":"spk_2","startTime":2009.09,"text":"Yeah, right. I don't know. We do 'separate 'stuff 'sometime's, right? It happen's, you know? Do you?","PodcastName":"The Ads Version: Hollywood Handbook","tags":[]}},{"_index":"handbook","_type":"_doc","id":"MBEBJnMByMrymAEmZj2g","_score":1,"_source":{"Episode":"Jeremy Levick and Rajat Suresh, Our Close Friends","speaker":"spk_2","startTime":2019.72,"text":"So, like, uh, like when you wrote locked down, Haye's wa's like that, Like, 'show's up with down. I","PodcastName":"The Ads Version: Hollywood Handbook","tags":["Haye"]}},{"_index":"handbook","_type":"_doc","id":"OBEBJnMByMrymAEmZj2g","_score":1,"_source":{"Episode":"Jeremy Levick and Rajat Suresh, Our Close Friends","speaker":"spk_2","startTime":2109.41,"text":"maybe he would ju'st reach for the donut and open the donut box. Of cour'se, the extra piece of the creature ha's more now into a dangerou's creature of it's own. And it''s going to bur'st from the donut box and attached to a deal''s neck.","PodcastName":"The Ads Version: Hollywood Handbook","tags":[]}},{"_index":"handbook","_type":"_doc","id":"PhEBJnMByMrymAEmZj2g","_score":1,"_source":{"Episode":"Jeremy Levick and Rajat Suresh, Our Close Friends","speaker":"spk_2","startTime":2176.44,"text":"'something. And I'm not getting the wording right. But he 'say's like, now I'll have a doughnut.","PodcastName":"The Ads Version: Hollywood Handbook","tags":[]}},{"_index":"handbook","_type":"_doc","id":"ShEBJnMByMrymAEmZj2g","_score":1,"_source":{"Episode":"Jeremy Levick and Rajat Suresh, Our Close Friends","speaker":"spk_0","startTime":2295.51,"text":"Ah, we're on a new CBS all acce's's 'show. Okay,","PodcastName":"The Ads Version: Hollywood Handbook","tags":["CBS"]}},{"_index":"handbook","_type":"_doc","id":"SxEBJnMByMrymAEmZj2g","_score":1,"_source":{"Episode":"Jeremy Levick and Rajat Suresh, Our Close Friends","speaker":"spk_1","startTime":2300.78,"text":"called and Car'son and Car'son wa's on that 'show. And your continuing the legacy of Johnny Car'son with that Joe? Exactly. Yeah, 'sort of. Ba'sic. Did Conan","PodcastName":"The Ads Version: Hollywood Handbook","tags":["Car'son","Car'son","Johnny Car'son","Joe","Conan"]}},{"_index":"handbook","_type":"_doc","id":"ThEBJnMByMrymAEmZj2g","_score":1,"_source":{"Episode":"Jeremy Levick and Rajat Suresh, Our Close Friends","speaker":"spk_0","startTime":2318.73,"text":"Very. There''s a rich comedy legacy on tuning out the new's. That''s right. Yeah, the Beatle's. I think they got their 'start learning are tuning out the new's.","PodcastName":"The Ads Version: Hollywood Handbook","tags":[]}}]